Metadata-Version: 2.1
Name: flake8-import-order-jwodder
Version: 0.1.0
Summary: Yet another import order style
Home-page: https://github.com/jwodder/flake8-import-order-jwodder
Author: John Thorvald Wodder II
Author-email: flake8-import-order-jwodder@varonathe.org
License: MIT
Project-URL: Source Code, https://github.com/jwodder/flake8-import-order-jwodder
Project-URL: Bug Tracker, https://github.com/jwodder/flake8-import-order-jwodder/issues
Project-URL: Say Thanks!, https://saythanks.io/to/jwodder
Keywords: code style,flake8,import,import order,linter
Platform: UNKNOWN
Classifier: Development Status :: 4 - Beta
Classifier: Programming Language :: Python :: 2
Classifier: Programming Language :: Python :: 2.7
Classifier: Programming Language :: Python :: 3
Classifier: Programming Language :: Python :: 3.5
Classifier: Programming Language :: Python :: 3.6
Classifier: Programming Language :: Python :: 3.7
Classifier: Programming Language :: Python :: 3.8
Classifier: Programming Language :: Python :: Implementation :: CPython
Classifier: Programming Language :: Python :: Implementation :: PyPy
Classifier: License :: OSI Approved :: MIT License
Classifier: Framework :: Flake8
Classifier: Intended Audience :: Developers
Classifier: Topic :: Software Development :: Libraries :: Python Modules
Classifier: Topic :: Software Development :: Quality Assurance
Requires-Python: !=3.0.*,!=3.1.*,!=3.2.*,!=3.3.*,!=3.4.*,<4,>=2.7
Requires-Dist: flake8-import-order (~=0.18)
